bean_inquiry/__init__.py
bean_inquiry/cli.py
bean_inquiry-0.3.0.dist-info/entry_points.txt
bean_inquiry-0.3.0.dist-info/licenses/LICENSE
bean_inquiry-0.3.0.dist-info/METADATA
bean_inquiry-0.3.0.dist-info/WHEEL
bean_inquiry-0.3.0.dist-info/RECORD
