Metadata-Version: 2.4
Name: bean-inquiry
Version: 0.3.0
Summary: A CLI tool to INject parameters into Beancount queries specified in your ledger
License-Expression: GPL-3.0-only
License-File: LICENSE
Author: aleyoscar
Author-email: mail@aleyoscar.com
Requires-Python: >=3.11
Classifier: Programming Language :: Python :: 3
Classifier: Programming Language :: Python :: 3.11
Classifier: Programming Language :: Python :: 3.12
Classifier: Programming Language :: Python :: 3.13
Classifier: Programming Language :: Python :: 3.14
Requires-Dist: beanquery (>=0.2.0,<0.3.0)
Project-URL: Homepage, https://github.com/aleyoscar/beancount-inquiry
Project-URL: Issues, https://github.com/aleyoscar/beancount-inquiry/issues
